spikeval/__init__.py
spikeval/metrics.py
spikeval-0.1.1.dist-info/WHEEL
spikeval-0.1.1.dist-info/METADATA
spikeval-0.1.1.dist-info/RECORD
