Metadata-Version: 2.1
Name: spikeval
Version: 0.1.1
Summary: ML evaluation/validation utilities by Spike
Author: Martín Villanueva
Author-email: mavillan@spikelab.xyz
Requires-Python: >=3.7.1,<4.0.0
Classifier: Programming Language :: Python :: 3
Classifier: Programming Language :: Python :: 3.8
Classifier: Programming Language :: Python :: 3.9
Requires-Dist: numpy (>=1.15,<2.0)
Requires-Dist: pandas (>=1.0,<2.0)
